src/cdnjs_cli/__about__.py
src/cdnjs_cli/__main__.py
src/cdnjs_cli/cli.py
src/cdnjs_cli/injector.py
src/cdnjs_cli/logger.py
src/cdnjs_cli/util.py
cdnjs_cli-0.0.4.dist-info/METADATA
cdnjs_cli-0.0.4.dist-info/WHEEL
cdnjs_cli-0.0.4.dist-info/entry_points.txt
cdnjs_cli-0.0.4.dist-info/licenses/LICENSE.txt
cdnjs_cli-0.0.4.dist-info/RECORD
